bomiot_example/__init__.py
bomiot_example/__version__.py
bomiot_example/bomiotconf.ini
bomiot_example/example.py
bomiot_example/fastapi_app/__init__.py
bomiot_example/fastapi_app/main.py
bomiot_example/files.py
bomiot_example/flask_app/__init__.py
bomiot_example/flask_app/main.py
bomiot_example/language/__init__.py
bomiot_example/language/en-US.toml
bomiot_example/language/zh-CN.toml
bomiot_example/media/__init__.py
bomiot_example/media/admin/favicon-origami-32.png
bomiot_example/media/admin/README.zh-CN (2).md
bomiot_example/media/admin/豆包 (1).png
bomiot_example/media/admin/豆包.png
bomiot_example/media/admin/豆包研究.pdf
bomiot_example/media/bomiotconf.en-US.md
bomiot_example/media/bomiotconf.zh-CN.md
bomiot_example/media/data.en-US.md
bomiot_example/media/data.zh-CN.md
bomiot_example/media/django.en-US.md
bomiot_example/media/django.zh-CN.md
bomiot_example/media/fastapi.en-US.md
bomiot_example/media/fastapi.zh-CN.md
bomiot_example/media/flask.en-US.md
bomiot_example/media/flask.zh-CN.md
bomiot_example/media/img/__init__.py
bomiot_example/media/img/logo.png
bomiot_example/media/inscription.en-US.md
bomiot_example/media/inscription.zh-CN.md
bomiot_example/media/interaction.en-US.md
bomiot_example/media/interaction.zh-CN.md
bomiot_example/media/mysql.en-US.md
bomiot_example/media/mysql.zh-CN.md
bomiot_example/media/observer.en-US.md
bomiot_example/media/observer.zh-CN.md
bomiot_example/media/performance.en-US.md
bomiot_example/media/performance.zh-CN.md
bomiot_example/media/permission.en-US.md
bomiot_example/media/permission.zh-CN.md
bomiot_example/media/poetry.en-US.md
bomiot_example/media/poetry.zh-CN.md
bomiot_example/media/postgresql.en-US.md
bomiot_example/media/postgresql.zh-CN.md
bomiot_example/media/README.en-US.md
bomiot_example/media/README.zh-CN.md
bomiot_example/media/scheduler.en-US.md
bomiot_example/media/scheduler.zh-CN.md
bomiot_example/media/server.en-US.md
bomiot_example/media/server.zh-CN.md
bomiot_example/media/setup.en-US.md
bomiot_example-1.0.2.dist-info/entry_points.txt
bomiot_example-1.0.2.dist-info/LICENSE
bomiot_example-1.0.2.dist-info/METADATA
bomiot_example-1.0.2.dist-info/WHEEL
bomiot_example-1.0.2.dist-info/RECORD
